test/__init__.py
test/test_evaluators.py
test/test_retrieval_evaluators.py
vision_evaluation/__init__.py
vision_evaluation/coco_evalcap_utils.py
vision_evaluation/coco_wrapper.py
vision_evaluation/evaluators.py
vision_evaluation/prediction_filters.py
vision_evaluation/resource_tight_evaluators.py
vision_evaluation/retrieval_evaluators.py
vision_evaluation-0.2.14.dist-info/LICENSE
vision_evaluation-0.2.14.dist-info/METADATA
vision_evaluation-0.2.14.dist-info/WHEEL
vision_evaluation-0.2.14.dist-info/top_level.txt
vision_evaluation-0.2.14.dist-info/RECORD
