Metadata-Version: 2.1
Name: vision-evaluation
Version: 0.2.14
Summary: Evaluation metric codes for various vision tasks.
Home-page: https://github.com/microsoft/vision-evaluation
Author: Ping Jin, Shohei Ono
License: MIT
Keywords: vision metric evaluation classification detection
Classifier: Development Status :: 4 - Beta
Classifier: Intended Audience :: Developers
Classifier: License :: OSI Approved :: MIT License
Classifier: Programming Language :: Python :: 3.7
Classifier: Programming Language :: Python :: 3.8
Classifier: Programming Language :: Python :: 3.9
Classifier: Programming Language :: Python :: 3.10
Requires-Python: >=3.7
License-File: LICENSE
Requires-Dist: numpy
Requires-Dist: scikit-learn (>=1.0)
Requires-Dist: pycocotools
Requires-Dist: opencv-python-headless
Requires-Dist: Pillow (>=6.2.2)
Provides-Extra: caption
Requires-Dist: pycocoevalcap ; extra == 'caption'
